Metadata-Version: 1.1
Name: init-subclass
Version: 0.0.1
Summary: backwards compatibility for __init_subclass__
Home-page: https://github.com/dpep/py_init_subclass
Author: Daniel Pepper
Author-email: UNKNOWN
License: MIT
Platform: any
Classifier: License :: OSI Approved :: MIT License
Classifier: Programming Language :: Python
Classifier: Topic :: Utilities
